{
  "entries": [
    {
      "dword0": 50,
      "dword4": 8,
      "dword8": 10,
      "dwordc": 1,
      "dword10": 0,
      "dword14": 0,
      "dword18": 50,
      "dword1c": 0,
      "dword20": 0,
      "dword24": 0,
      "dword28": 0,
      "gap2c": 256,
      "word2e": 0,
      "dword30": 0,
      "dword34": 1067869798,
      "float38": 1.0,
      "float3c": 1.0,
      "byte40": 1,
      "map_id": 1500,
      "game_name": "TU Slayer",
      "game_variant_file_name": "tu1_slayer_team_squad",
      "map_name": "Condemned",
      "map_variant_file_name": "condemned_default",
      "unknown3": 0
    },
    {
      "dword0": 50,
      "dword4": 8,
      "dword8": 10,
      "dwordc": 1,
      "dword10": 0,
      "dword14": 0,
      "dword18": 50,
      "dword1c": 0,
      "dword20": 0,
      "dword24": 0,
      "dword28": 0,
      "gap2c": 256,
      "word2e": 1,
      "dword30": 0,
      "dword34": 1067869798,
      "float38": 1.0,
      "float3c": 1.0,
      "byte40": 1,
      "map_id": 1500,
      "game_name": "TU Slayer DMRs",
      "game_variant_file_name": "tu1_slayer_team_squad_dmr",
      "map_name": "Condemned",
      "map_variant_file_name": "condemned_default",
      "unknown3": 0
    },
    {
      "dword0": 50,
      "dword4": 8,
      "dword8": 10,
      "dwordc": 1,
      "dword10": 0,
      "dword14": 0,
      "dword18": 50,
      "dword1c": 0,
      "dword20": 0,
      "dword24": 0,
      "dword28": 0,
      "gap2c": 256,
      "word2e": 2,
      "dword30": 0,
      "dword34": 1067869798,
      "float38": 1.0,
      "float3c": 1.0,
      "byte40": 1,
      "map_id": 1500,
      "game_name": "TU Slayer",
      "game_variant_file_name": "tu1_slayer_team_squad",
      "map_name": "Uplink",
      "map_variant_file_name": "condemned_uplink",
      "unknown3": 0
    },
    {
      "dword0": 50,
      "dword4": 8,
      "dword8": 10,
      "dwordc": 1,
      "dword10": 0,
      "dword14": 0,
      "dword18": 50,
      "dword1c": 0,
      "dword20": 0,
      "dword24": 0,
      "dword28": 0,
      "gap2c": 256,
      "word2e": 3,
      "dword30": 0,
      "dword34": 1067869798,
      "float38": 1.0,
      "float3c": 1.0,
      "byte40": 1,
      "map_id": 1500,
      "game_name": "TU Slayer DMRs",
      "game_variant_file_name": "tu1_slayer_team_squad_dmr",
      "map_name": "Uplink",
      "map_variant_file_name": "condemned_uplink",
      "unknown3": 0
    },
    {
      "dword0": 80,
      "dword4": 8,
      "dword8": 10,
      "dwordc": 1,
      "dword10": 0,
      "dword14": 0,
      "dword18": 50,
      "dword1c": 0,
      "dword20": 0,
      "dword24": 0,
      "dword28": 0,
      "gap2c": 256,
      "word2e": 4,
      "dword30": 0,
      "dword34": 1067869798,
      "float38": 1.0,
      "float3c": 1.0,
      "byte40": 1,
      "map_id": 2004,
      "game_name": "TU Slayer DMRs",
      "game_variant_file_name": "tu1_slayer_team_squad_dmr",
      "map_name": "Tempest",
      "map_variant_file_name": "tempest_default",
      "unknown3": 0
    },
    {
      "dword0": 50,
      "dword4": 8,
      "dword8": 10,
      "dwordc": 1,
      "dword10": 0,
      "dword14": 0,
      "dword18": 50,
      "dword1c": 0,
      "dword20": 0,
      "dword24": 0,
      "dword28": 0,
      "gap2c": 256,
      "word2e": 5,
      "dword30": 0,
      "dword34": 1067869798,
      "float38": 1.0,
      "float3c": 1.0,
      "byte40": 1,
      "map_id": 2001,
      "game_name": "TU Slayer",
      "game_variant_file_name": "tu1_slayer_team_squad",
      "map_name": "Unanchored",
      "map_variant_file_name": "unanchored_default",
      "unknown3": 0
    },
    {
      "dword0": 50,
      "dword4": 8,
      "dword8": 10,
      "dwordc": 1,
      "dword10": 0,
      "dword14": 0,
      "dword18": 50,
      "dword1c": 0,
      "dword20": 0,
      "dword24": 0,
      "dword28": 0,
      "gap2c": 256,
      "word2e": 6,
      "dword30": 0,
      "dword34": 1067869798,
      "float38": 1.0,
      "float3c": 1.0,
      "byte40": 1,
      "map_id": 2001,
      "game_name": "TU Slayer DMRs",
      "game_variant_file_name": "tu1_slayer_team_squad_dmr",
      "map_name": "Unanchored",
      "map_variant_file_name": "unanchored_default",
      "unknown3": 0
    },
    {
      "dword0": 100,
      "dword4": 8,
      "dword8": 10,
      "dwordc": 9,
      "dword10": 0,
      "dword14": 0,
      "dword18": 50,
      "dword1c": 0,
      "dword20": 0,
      "dword24": 0,
      "dword28": 0,
      "gap2c": 256,
      "word2e": 7,
      "dword30": 0,
      "dword34": 1067869798,
      "float38": 1.0,
      "float3c": 1.0,
      "byte40": 1,
      "map_id": 10060,
      "game_name": "TU Slayer",
      "game_variant_file_name": "tu1_slayer_team_squad",
      "map_name": "High Noon",
      "map_variant_file_name": "hangemhigh_default",
      "unknown3": 0
    },
    {
      "dword0": 100,
      "dword4": 8,
      "dword8": 10,
      "dwordc": 9,
      "dword10": 0,
      "dword14": 0,
      "dword18": 50,
      "dword1c": 0,
      "dword20": 0,
      "dword24": 0,
      "dword28": 0,
      "gap2c": 256,
      "word2e": 8,
      "dword30": 0,
      "dword34": 1067869798,
      "float38": 1.0,
      "float3c": 1.0,
      "byte40": 1,
      "map_id": 10060,
      "game_name": "TU Slayer DMRs",
      "game_variant_file_name": "tu1_slayer_team_squad_dmr",
      "map_name": "High Noon",
      "map_variant_file_name": "hangemhigh_default",
      "unknown3": 0
    },
    {
      "dword0": 100,
      "dword4": 8,
      "dword8": 10,
      "dwordc": 9,
      "dword10": 0,
      "dword14": 0,
      "dword18": 50,
      "dword1c": 0,
      "dword20": 0,
      "dword24": 0,
      "dword28": 0,
      "gap2c": 256,
      "word2e": 9,
      "dword30": 0,
      "dword34": 1067869798,
      "float38": 1.0,
      "float3c": 1.0,
      "byte40": 1,
      "map_id": 10010,
      "game_name": "TU Slayer",
      "game_variant_file_name": "tu1_slayer_team_squad",
      "map_name": "Penance",
      "map_variant_file_name": "damnation_default",
      "unknown3": 0
    },
    {
      "dword0": 100,
      "dword4": 8,
      "dword8": 10,
      "dwordc": 9,
      "dword10": 0,
      "dword14": 0,
      "dword18": 50,
      "dword1c": 0,
      "dword20": 0,
      "dword24": 0,
      "dword28": 0,
      "gap2c": 256,
      "word2e": 10,
      "dword30": 0,
      "dword34": 1067869798,
      "float38": 1.0,
      "float3c": 1.0,
      "byte40": 1,
      "map_id": 10010,
      "game_name": "TU Slayer DMRs",
      "game_variant_file_name": "tu1_slayer_team_squad_dmr",
      "map_name": "Penance",
      "map_variant_file_name": "damnation_default",
      "unknown3": 0
    },
    {
      "dword0": 100,
      "dword4": 8,
      "dword8": 10,
      "dwordc": 9,
      "dword10": 0,
      "dword14": 0,
      "dword18": 50,
      "dword1c": 0,
      "dword20": 0,
      "dword24": 0,
      "dword28": 0,
      "gap2c": 256,
      "word2e": 11,
      "dword30": 0,
      "dword34": 1067869798,
      "float38": 1.0,
      "float3c": 1.0,
      "byte40": 1,
      "map_id": 10070,
      "game_name": "TU Slayer",
      "game_variant_file_name": "tu1_slayer_team_squad",
      "map_name": "Solitary",
      "map_variant_file_name": "prisoner_default",
      "unknown3": 0
    },
    {
      "dword0": 100,
      "dword4": 8,
      "dword8": 10,
      "dwordc": 9,
      "dword10": 0,
      "dword14": 0,
      "dword18": 50,
      "dword1c": 0,
      "dword20": 0,
      "dword24": 0,
      "dword28": 0,
      "gap2c": 256,
      "word2e": 12,
      "dword30": 0,
      "dword34": 1067869798,
      "float38": 1.0,
      "float3c": 1.0,
      "byte40": 1,
      "map_id": 10070,
      "game_name": "TU Slayer DMRs",
      "game_variant_file_name": "tu1_slayer_team_squad_dmr",
      "map_name": "Solitary",
      "map_variant_file_name": "prisoner_default",
      "unknown3": 0
    },
    {
      "dword0": 100,
      "dword4": 8,
      "dword8": 10,
      "dwordc": 9,
      "dword10": 0,
      "dword14": 0,
      "dword18": 50,
      "dword1c": 0,
      "dword20": 0,
      "dword24": 0,
      "dword28": 0,
      "gap2c": 256,
      "word2e": 13,
      "dword30": 0,
      "dword34": 1067869798,
      "float38": 1.0,
      "float3c": 1.0,
      "byte40": 1,
      "map_id": 10020,
      "game_name": "TU Slayer",
      "game_variant_file_name": "tu1_slayer_team_squad",
      "map_name": "Battle Canyon",
      "map_variant_file_name": "beaver_creek_default",
      "unknown3": 0
    },
    {
      "dword0": 100,
      "dword4": 8,
      "dword8": 10,
      "dwordc": 9,
      "dword10": 0,
      "dword14": 0,
      "dword18": 50,
      "dword1c": 0,
      "dword20": 0,
      "dword24": 0,
      "dword28": 0,
      "gap2c": 256,
      "word2e": 14,
      "dword30": 0,
      "dword34": 1067869798,
      "float38": 1.0,
      "float3c": 1.0,
      "byte40": 1,
      "map_id": 10020,
      "game_name": "TU Slayer DMRs",
      "game_variant_file_name": "tu1_slayer_team_squad_dmr",
      "map_name": "Battle Canyon",
      "map_variant_file_name": "beaver_creek_default",
      "unknown3": 0
    },
    {
      "dword0": 10,
      "dword4": 8,
      "dword8": 10,
      "dwordc": 9,
      "dword10": 0,
      "dword14": 0,
      "dword18": 50,
      "dword1c": 0,
      "dword20": 0,
      "dword24": 0,
      "dword28": 0,
      "gap2c": 0,
      "word2e": 15,
      "dword30": 0,
      "dword34": 0,
      "float38": 0.0,
      "float3c": 0.0,
      "byte40": 0,
      "map_id": 3006,
      "game_name": "TU Slayer",
      "game_variant_file_name": "tu1_slayer_team_squad",
      "map_name": "Asylum",
      "map_variant_file_name": "coastline_asylum_default",
      "unknown3": 0
    },
    {
      "dword0": 10,
      "dword4": 8,
      "dword8": 10,
      "dwordc": 9,
      "dword10": 0,
      "dword14": 0,
      "dword18": 50,
      "dword1c": 0,
      "dword20": 0,
      "dword24": 0,
      "dword28": 0,
      "gap2c": 0,
      "word2e": 16,
      "dword30": 0,
      "dword34": 0,
      "float38": 0.0,
      "float3c": 0.0,
      "byte40": 0,
      "map_id": 3006,
      "game_name": "TU Slayer DMRs",
      "game_variant_file_name": "tu1_slayer_team_squad_dmr",
      "map_name": "Asylum",
      "map_variant_file_name": "coastline_asylum_default",
      "unknown3": 0
    },
    {
      "dword0": 10,
      "dword4": 8,
      "dword8": 10,
      "dwordc": 9,
      "dword10": 0,
      "dword14": 0,
      "dword18": 50,
      "dword1c": 0,
      "dword20": 0,
      "dword24": 0,
      "dword28": 0,
      "gap2c": 0,
      "word2e": 17,
      "dword30": 0,
      "dword34": 0,
      "float38": 0.0,
      "float3c": 0.0,
      "byte40": 0,
      "map_id": 3006,
      "game_name": "TU Slayer DMRs",
      "game_variant_file_name": "tu1_slayer_team_squad_dmr",
      "map_name": "Uncaged",
      "map_variant_file_name": "coastline_uncaged_default",
      "unknown3": 0
    },
    {
      "dword0": 10,
      "dword4": 8,
      "dword8": 10,
      "dwordc": 9,
      "dword10": 0,
      "dword14": 0,
      "dword18": 50,
      "dword1c": 0,
      "dword20": 0,
      "dword24": 0,
      "dword28": 0,
      "gap2c": 0,
      "word2e": 18,
      "dword30": 0,
      "dword34": 0,
      "float38": 0.0,
      "float3c": 0.0,
      "byte40": 0,
      "map_id": 1150,
      "game_name": "TU Slayer",
      "game_variant_file_name": "tu1_slayer_team_squad",
      "map_name": "Reflection",
      "map_variant_file_name": "ivory_tower_default",
      "unknown3": 0
    },
    {
      "dword0": 10,
      "dword4": 8,
      "dword8": 10,
      "dwordc": 9,
      "dword10": 0,
      "dword14": 0,
      "dword18": 50,
      "dword1c": 0,
      "dword20": 0,
      "dword24": 0,
      "dword28": 0,
      "gap2c": 0,
      "word2e": 19,
      "dword30": 0,
      "dword34": 0,
      "float38": 0.0,
      "float3c": 0.0,
      "byte40": 0,
      "map_id": 1150,
      "game_name": "TU Slayer DMRs",
      "game_variant_file_name": "tu1_slayer_team_squad_dmr",
      "map_name": "Reflection",
      "map_variant_file_name": "ivory_tower_default",
      "unknown3": 0
    },
    {
      "dword0": 10,
      "dword4": 8,
      "dword8": 10,
      "dwordc": 9,
      "dword10": 0,
      "dword14": 0,
      "dword18": 50,
      "dword1c": 0,
      "dword20": 0,
      "dword24": 0,
      "dword28": 0,
      "gap2c": 0,
      "word2e": 20,
      "dword30": 0,
      "dword34": 0,
      "float38": 0.0,
      "float3c": 0.0,
      "byte40": 0,
      "map_id": 1020,
      "game_name": "TU Slayer",
      "game_variant_file_name": "tu1_slayer_team_squad",
      "map_name": "Countdown",
      "map_variant_file_name": "launch_station_default",
      "unknown3": 0
    },
    {
      "dword0": 10,
      "dword4": 8,
      "dword8": 10,
      "dwordc": 9,
      "dword10": 0,
      "dword14": 0,
      "dword18": 50,
      "dword1c": 0,
      "dword20": 0,
      "dword24": 0,
      "dword28": 0,
      "gap2c": 0,
      "word2e": 21,
      "dword30": 0,
      "dword34": 0,
      "float38": 0.0,
      "float3c": 0.0,
      "byte40": 0,
      "map_id": 1020,
      "game_name": "TU Slayer DMRs",
      "game_variant_file_name": "tu1_slayer_team_squad_dmr",
      "map_name": "Countdown",
      "map_variant_file_name": "launch_station_default",
      "unknown3": 0
    },
    {
      "dword0": 10,
      "dword4": 8,
      "dword8": 10,
      "dwordc": 9,
      "dword10": 0,
      "dword14": 0,
      "dword18": 50,
      "dword1c": 0,
      "dword20": 0,
      "dword24": 0,
      "dword28": 0,
      "gap2c": 0,
      "word2e": 22,
      "dword30": 0,
      "dword34": 0,
      "float38": 0.0,
      "float3c": 0.0,
      "byte40": 0,
      "map_id": 1035,
      "game_name": "TU Slayer DMRs",
      "game_variant_file_name": "tu1_slayer_team_squad_dmr",
      "map_name": "Boardwalk",
      "map_variant_file_name": "panoptical_default",
      "unknown3": 0
    },
    {
      "dword0": 10,
      "dword4": 8,
      "dword8": 10,
      "dwordc": 9,
      "dword10": 0,
      "dword14": 0,
      "dword18": 50,
      "dword1c": 0,
      "dword20": 0,
      "dword24": 0,
      "dword28": 0,
      "gap2c": 0,
      "word2e": 23,
      "dword30": 0,
      "dword34": 0,
      "float38": 0.0,
      "float3c": 0.0,
      "byte40": 0,
      "map_id": 1055,
      "game_name": "TU Slayer",
      "game_variant_file_name": "tu1_slayer_team_squad",
      "map_name": "Powerhouse",
      "map_variant_file_name": "settlement_default",
      "unknown3": 0
    },
    {
      "dword0": 10,
      "dword4": 8,
      "dword8": 10,
      "dwordc": 9,
      "dword10": 0,
      "dword14": 0,
      "dword18": 50,
      "dword1c": 0,
      "dword20": 0,
      "dword24": 0,
      "dword28": 0,
      "gap2c": 0,
      "word2e": 24,
      "dword30": 0,
      "dword34": 0,
      "float38": 0.0,
      "float3c": 0.0,
      "byte40": 0,
      "map_id": 1055,
      "game_name": "TU Slayer DMRs",
      "game_variant_file_name": "tu1_slayer_team_squad_dmr",
      "map_name": "Powerhouse",
      "map_variant_file_name": "settlement_default",
      "unknown3": 0
    },
    {
      "dword0": 10,
      "dword4": 8,
      "dword8": 10,
      "dwordc": 9,
      "dword10": 0,
      "dword14": 0,
      "dword18": 50,
      "dword1c": 0,
      "dword20": 0,
      "dword24": 0,
      "dword28": 0,
      "gap2c": 0,
      "word2e": 25,
      "dword30": 0,
      "dword34": 0,
      "float38": 0.0,
      "float3c": 0.0,
      "byte40": 0,
      "map_id": 1040,
      "game_name": "TU Slayer",
      "game_variant_file_name": "tu1_slayer_team_squad",
      "map_name": "Arena Zealot",
      "map_variant_file_name": "zealot_arena",
      "unknown3": 0
    },
    {
      "dword0": 10,
      "dword4": 8,
      "dword8": 10,
      "dwordc": 9,
      "dword10": 0,
      "dword14": 0,
      "dword18": 50,
      "dword1c": 0,
      "dword20": 0,
      "dword24": 0,
      "dword28": 0,
      "gap2c": 0,
      "word2e": 26,
      "dword30": 0,
      "dword34": 0,
      "float38": 0.0,
      "float3c": 0.0,
      "byte40": 0,
      "map_id": 1040,
      "game_name": "TU Slayer DMRs",
      "game_variant_file_name": "tu1_slayer_team_squad_dmr",
      "map_name": "Arena Zealot",
      "map_variant_file_name": "zealot_arena",
      "unknown3": 0
    }
  ]
}